Metadata-Version: 2.1
Name: odoo14-addon-partner_company_group
Version: 14.0.1.2.0
Summary: Adds the possibility to add a company group to a company
Home-page: https://github.com/OCA/partner-contact
Author: Camptocamp SA, Odoo Community Association (OCA)
Author-email: support@odoo-community.org
License: AGPL-3
Classifier: Programming Language :: Python
Classifier: Framework :: Odoo
Classifier: Framework :: Odoo :: 14.0
Classifier: License :: OSI Approved :: GNU Affero General Public License v3
Requires-Python: >=3.6
Requires-Dist: odoo <14.1dev,>=14.0a
